Topsis_102197018/102197018.py
Topsis_102197018/__init__.py
Topsis_102197018-0.0.1.dist-info/LICENSE.txt
Topsis_102197018-0.0.1.dist-info/METADATA
Topsis_102197018-0.0.1.dist-info/WHEEL
Topsis_102197018-0.0.1.dist-info/entry_points.txt
Topsis_102197018-0.0.1.dist-info/top_level.txt
Topsis_102197018-0.0.1.dist-info/RECORD
