Metadata-Version: 2.1
Name: Topsis-102197018
Version: 0.0.1
Summary: A TOPSIS python Package
Author: Gaurav Gupta
Author-email: ggupta5_be20@thapar.edu
Classifier: License :: OSI Approved :: MIT License
Classifier: Programming Language :: Python :: 3
Classifier: Programming Language :: Python :: 3.7
License-File: LICENSE.txt
Requires-Dist: numpy
Requires-Dist: pandas
Requires-Dist: sys
